cinder/404.html
cinder/__init__.py
cinder/base.html
cinder/content.html
cinder/keyboard-modal.html
cinder/main.html
cinder/mkdocs_theme.yml
cinder/nav-sub.html
cinder/nav.html
cinder/search-modal.html
cinder/toc.html
cinder/css/base.css
cinder/css/base.min.css
cinder/css/bootstrap-custom.css
cinder/css/bootstrap-custom.min.css
cinder/css/cinder.css
cinder/css/cinder.min.css
cinder/css/highlight.css
cinder/css/highlight.min.css
cinder/fonts/fontawesome-webfont.eot
cinder/fonts/fontawesome-webfont.svg
cinder/fonts/fontawesome-webfont.ttf
cinder/fonts/fontawesome-webfont.woff
cinder/img/favicon.ico
cinder/img/grid1.png
cinder/img/grid10.png
cinder/img/grid11.png
cinder/img/grid12.png
cinder/img/grid13.png
cinder/img/grid14.png
cinder/img/grid15.png
cinder/img/grid16.png
cinder/img/grid17.png
cinder/img/grid18.png
cinder/img/grid19.png
cinder/img/grid2.png
cinder/img/grid20.png
cinder/img/grid3.png
cinder/img/grid4.png
cinder/img/grid5.png
cinder/img/grid6.png
cinder/img/grid7.png
cinder/img/grid8.png
cinder/img/grid9.png
cinder/js/base.js
cinder/js/bootstrap-3.0.3.min.js
cinder/js/highlight.pack.js
mkdocs_cinder-1.1.0.dist-info/LICENSE.md
mkdocs_cinder-1.1.0.dist-info/METADATA
mkdocs_cinder-1.1.0.dist-info/WHEEL
mkdocs_cinder-1.1.0.dist-info/entry_points.txt
mkdocs_cinder-1.1.0.dist-info/top_level.txt
mkdocs_cinder-1.1.0.dist-info/RECORD
