Metadata-Version: 2.1
Name: mkdocs-cinder
Version: 1.1.0
Summary: A clean responsive theme for the MkDocs static documentation site generator
Home-page: https://github.com/chrissimpkins/cinder
Author: Christopher Simpkins
Author-email: chris@sourcefoundry.org
License: MIT
Platform: UNKNOWN
